[
    {   "id":1,
        "Name":"Healthy Meal Plan",
        "description":"How we dream about our future",
        "price":249,
        "img": "https://i.ibb.co/1Mpf38w/breakfast1.png"
    },
    {   "id":2,
        "Name":"Healthy Meal Plan",
        "description":"How we dream about our future",
        "price":249,
        "img": "https://i.ibb.co/1Mpf38w/breakfast2.png"
    },
    {   "id":3,
        "Name":"Healthy Meal Plan",
        "description":"How we dream about our future",
        "price":249,
        "img": "https://i.ibb.co/1Mpf38w/breakfast3.png"
    },
    {   "id":4,
        "Name":"Healthy Meal Plan",
        "description":"How we dream about our future",
        "price":249,
        "img": "https://i.ibb.co/1Mpf38w/breakfast3.png"
    },
    {   "id":5,
        "Name":"Healthy Meal Plan",
        "description":"How we dream about our future",
        "price":249,
        "img": "https://i.ibb.co/W3NdrLq/lunch4.png"
    },
    {   "id":6,
        "Name":"Fried Chicken Bento",
        "description":"How we dream about our future",
        "price":109,
        "img": "https://i.ibb.co/jwRs7x1/lunch5.png"
    },
    {   "id":7,
        "Name":"Indian Lunch",
        "description":"How we dream about our future",
        "price":199,
        "img": "https://i.ibb.co/yd49nP8/lunch6.png"
    },
    {   "id":8,
        "Name":"Indian Lunch",
        "description":"How we dream about our future",
        "price":199,
        "img": "https://i.ibb.co/yd49nP8/lunch6.png"
    },
    {   "id":9,
        "Name":"Salmon With sea food salad",
        "description":"How we dream about our future",
        "price":399,
        "img": "https://i.ibb.co/yd49nP8/dinner1.png"
    },
    {   "id":10,
        "Name":"Lemony salmon picca",
        "description":"How we dream about our future",
        "price":499,
        "img": "https://i.ibb.co/yd49nP8/dinner2.png"
    },
    {   "id":11,
        "Name":"Indian Lunch",
        "description":"How we dream about our future",
        "price":299,
        "img": "https://i.ibb.co/yd49nP8/dinner3.png"
    },
    {   "id":12,
        "Name":"Indian Lunch",
        "description":"How we dream about our future",
        "price":299,
        "img": "https://i.ibb.co/yd49nP8/dinner3.png"
    }
]
